README.md
setup.cfg
setup.py
dsnd_probabilities_1/Binomialdistribution.py
dsnd_probabilities_1/Gaussiandistribution.py
dsnd_probabilities_1/Generaldistribution.py
dsnd_probabilities_1/__init__.py
dsnd_probabilities_1.egg-info/PKG-INFO
dsnd_probabilities_1.egg-info/SOURCES.txt
dsnd_probabilities_1.egg-info/dependency_links.txt
dsnd_probabilities_1.egg-info/not-zip-safe
dsnd_probabilities_1.egg-info/top_level.txt