Metadata-Version: 1.0
Name: dsnd-probabilities-1
Version: 1.0
Summary: Gaussian and Binomial distributions
Home-page: UNKNOWN
Author: Beatriz Farias
Author-email: beatrizfarias.engcomp@gmail.com
License: UNKNOWN
Platform: UNKNOWN
